bisheng_langchain/__init__.py
bisheng_langchain/agents/__init__.py
bisheng_langchain/agents/chatglm_functions_agent/__init__.py
bisheng_langchain/agents/chatglm_functions_agent/base.py
bisheng_langchain/agents/chatglm_functions_agent/output_parser.py
bisheng_langchain/agents/chatglm_functions_agent/prompt.py
bisheng_langchain/agents/llm_functions_agent/__init__.py
bisheng_langchain/agents/llm_functions_agent/base.py
bisheng_langchain/autogen_role/__init__.py
bisheng_langchain/autogen_role/assistant.py
bisheng_langchain/autogen_role/custom.py
bisheng_langchain/autogen_role/groupchat_manager.py
bisheng_langchain/autogen_role/user.py
bisheng_langchain/chains/__init__.py
bisheng_langchain/chains/autogen/__init__.py
bisheng_langchain/chains/autogen/auto_gen.py
bisheng_langchain/chains/combine_documents/__init__.py
bisheng_langchain/chains/combine_documents/stuff.py
bisheng_langchain/chains/conversational_retrieval/__init__.py
bisheng_langchain/chains/conversational_retrieval/base.py
bisheng_langchain/chains/loader_output.py
bisheng_langchain/chains/qa_generation/__init__.py
bisheng_langchain/chains/qa_generation/base.py
bisheng_langchain/chains/qa_generation/base_v2.py
bisheng_langchain/chains/qa_generation/prompt.py
bisheng_langchain/chains/qa_generation/prompt_v2.py
bisheng_langchain/chains/question_answering/__init__.py
bisheng_langchain/chains/retrieval/__init__.py
bisheng_langchain/chains/retrieval/retrieval_chain.py
bisheng_langchain/chains/router/__init__.py
bisheng_langchain/chains/router/multi_rule.py
bisheng_langchain/chains/router/rule_router.py
bisheng_langchain/chains/transform.py
bisheng_langchain/chat_models/__init__.py
bisheng_langchain/chat_models/host_llm.py
bisheng_langchain/chat_models/interface/__init__.py
bisheng_langchain/chat_models/interface/minimax.py
bisheng_langchain/chat_models/interface/openai.py
bisheng_langchain/chat_models/interface/types.py
bisheng_langchain/chat_models/interface/utils.py
bsrag_langchain-0.3.8.0.dist-info/METADATA
bsrag_langchain-0.3.8.0.dist-info/WHEEL
bsrag_langchain-0.3.8.0.dist-info/RECORD
