Metadata-Version: 2.1
Name: bsrag-langchain
Version: 0.3.8.0
Summary: 
Author: jun.xiang
Author-email: jun.xiang@extremevision.com.cn
Requires-Python: >=3.10,<4.0
Classifier: Programming Language :: Python :: 3
Classifier: Programming Language :: Python :: 3.10
Classifier: Programming Language :: Python :: 3.11
Classifier: Programming Language :: Python :: 3.12
Classifier: Programming Language :: Python :: 3.13
Requires-Dist: bisheng-pyautogen (>=0.3.2,<0.4.0)
Requires-Dist: bisheng-ragas (>=1.0.0,<1.1.0)
Requires-Dist: elasticsearch (>=8.17.1,<8.18.0)
Requires-Dist: filetype (>=1.2.0,<1.3.0)
Requires-Dist: jieba (>=0.42.1,<0.43.0)
Requires-Dist: langchain-openai (>=0.1.5,<0.2.0)
Requires-Dist: langgraph (>=0.0.50,<0.1.0)
Requires-Dist: llama-index (>=0.9.48,<0.10.0)
Requires-Dist: openai (>=1.14.3,<1.15.0)
Requires-Dist: opencv-python (>=4.5.5.64,<4.6.0.0)
Requires-Dist: pillow (>=9.5.0,<9.6.0)
Requires-Dist: pydantic (>=1.10.13,<1.11.0)
Requires-Dist: pymupdf (>=1.23.8,<1.24.0)
Requires-Dist: shapely (>=2.0.2,<2.1.0)
Requires-Dist: websocket-client (>=1.8.0,<1.9.0)
Requires-Dist: zhipuai (>=2.1.5.20250106,<2.2.0.0)
